memusage
